proteoclade/__init__.py
proteoclade/pcannotate.py
proteoclade/pcconstants.py
proteoclade/pcdb.py
proteoclade/pcquant.py
proteoclade/pcutilities.py
proteoclade-1.0.1.dist-info/LICENSE
proteoclade-1.0.1.dist-info/METADATA
proteoclade-1.0.1.dist-info/WHEEL
proteoclade-1.0.1.dist-info/top_level.txt
proteoclade-1.0.1.dist-info/RECORD
