Metadata-Version: 2.1
Name: proteoclade
Version: 1.0.1
Summary: Package for taxon-specific bottom-up proteomics
Home-page: https://github.com/heldlab/proteoclade
Author: Arshag Mooradian
Author-email: mooradian@wustl.edu
License: UNKNOWN
Platform: UNKNOWN
Classifier: Programming Language :: Python :: 3
Classifier: License :: OSI Approved :: GNU General Public License v3 (GPLv3)
Classifier: Operating System :: OS Independent
